MANIFEST.in
README.md
README.rst
readme.rst
requirements.txt
setup.py
floresta/__init__.py
floresta/cli.py
floresta/core.py
floresta/datastructures.py
floresta/exceptions.py
floresta/log.py
floresta/models.py
floresta/parser.py
floresta/version.py
floresta.egg-info/PKG-INFO
floresta.egg-info/SOURCES.txt
floresta.egg-info/dependency_links.txt
floresta.egg-info/entry_points.txt
floresta.egg-info/requires.txt
floresta.egg-info/top_level.txt