Metadata-Version: 1.0
Name: floresta
Version: 0.0.2
Summary: Amazon VPC deployment tool
Home-page: http://github.com/gabrielfalcao/floresta
Author: Gabriel Falcao
Author-email: gabriel@nacaolivre.org
License: MIT
Platform: UNKNOWN
